pySESL/__init__.py
pySESL/historical.py
pySESL/io.py
pySESL/project.py
pySESL-0.4.0.dist-info/AUTHORS.rst
pySESL-0.4.0.dist-info/LICENSE
pySESL-0.4.0.dist-info/METADATA
pySESL-0.4.0.dist-info/WHEEL
pySESL-0.4.0.dist-info/top_level.txt
pySESL-0.4.0.dist-info/RECORD
